auth_lib/__init__.py
auth_lib/models.py
auth_lib/services.py
auth_lib_services-0.0.7.dist-info/METADATA
auth_lib_services-0.0.7.dist-info/WHEEL
auth_lib_services-0.0.7.dist-info/top_level.txt
auth_lib_services-0.0.7.dist-info/RECORD
